LICENSE
MANIFEST.in
README.md
package.json
setup.py
dash_force_graph/DashForceGraph.py
dash_force_graph/__init__.py
dash_force_graph/_imports_.py
dash_force_graph/dash_force_graph.min.js
dash_force_graph/dash_force_graph.min.js.map
dash_force_graph/metadata.json
dash_force_graph/package-info.json
dash_force_graph.egg-info/PKG-INFO
dash_force_graph.egg-info/SOURCES.txt
dash_force_graph.egg-info/dependency_links.txt
dash_force_graph.egg-info/top_level.txt
tests/test_usage.py