Metadata-Version: 2.1
Name: dash_force_graph
Version: 0.0.1
Summary: Dash Force Graph
Author: Siddhartha Chakraborty <techiesid1985@gmail.com>
License: MIT
Classifier: Framework :: Dash
License-File: LICENSE
